appsync_resolver_uploader/__init__.py
appsync_resolver_uploader/__main__.py
appsync_resolver_uploader-1.0.0.dist-info/LICENSE
appsync_resolver_uploader-1.0.0.dist-info/METADATA
appsync_resolver_uploader-1.0.0.dist-info/WHEEL
appsync_resolver_uploader-1.0.0.dist-info/top_level.txt
appsync_resolver_uploader-1.0.0.dist-info/RECORD
