Metadata-Version: 2.1
Name: appsync-resolver-uploader
Version: 1.0.0
Summary: Creates or updates an AWS AppSync resolver
Home-page: https://github.com/QuiNovas/appsync-resolver-uploader
Author: Joseph Wortmann
Author-email: joseph.wortmann@gmail.com
License: APL 2.0
Keywords: quinovas
Platform: UNKNOWN
Classifier: Development Status :: 5 - Production/Stable
Classifier: Topic :: System :: Software Distribution
Classifier: Intended Audience :: Developers
Classifier: License :: OSI Approved :: Apache Software License
Classifier: Programming Language :: Python :: 2.7
Requires-Dist: argparse
Requires-Dist: boto3 (>=1.9.156)
